Total5/__init__.py
Total5/core.py
total5-0.0.2.dist-info/licenses/LICENSE
total5-0.0.2.dist-info/METADATA
total5-0.0.2.dist-info/WHEEL
total5-0.0.2.dist-info/top_level.txt
total5-0.0.2.dist-info/RECORD
