Metadata-Version: 2.4
Name: Total5
Version: 0.0.2
Summary: Total.js v5 integration (Pypeline) with Python
Author: Peter Širka
Author-email: Peter Širka <petersirka@gmail.com>
Project-URL: Homepage, https://github.com/totaljs/pytotal
Classifier: Programming Language :: Python :: 3
Classifier: Operating System :: OS Independent
Requires-Python: >=3.8
License-File: LICENSE
Dynamic: author
Dynamic: license-file
Dynamic: requires-python
